carbonplan_data/__init__.py
carbonplan_data/metadata.py
carbonplan_data/utils.py
carbonplan_data/catalogs/fia.yaml
carbonplan_data/catalogs/fluxnet.yaml
carbonplan_data/catalogs/gcp.yaml
carbonplan_data/catalogs/gridmet.yaml
carbonplan_data/catalogs/grids.yaml
carbonplan_data/catalogs/maca.yaml
carbonplan_data/catalogs/master.yaml
carbonplan_data/catalogs/mtbs.yaml
carbonplan_data/catalogs/nftd.yaml
carbonplan_data/catalogs/nlcd.yaml
carbonplan_data/catalogs/projects.yaml
carbonplan_data/catalogs/spawnetal2020.yaml
carbonplan_data/catalogs/terraclimate.yaml
carbonplan_data/tests/__init__.py
carbonplan_data/tests/test_catalogs.py
carbonplan_data/tests/test_utils.py
carbonplan_data-0.4.4.dist-info/LICENSE
carbonplan_data-0.4.4.dist-info/METADATA
carbonplan_data-0.4.4.dist-info/WHEEL
carbonplan_data-0.4.4.dist-info/top_level.txt
carbonplan_data-0.4.4.dist-info/RECORD
