Metadata-Version: 2.1
Name: carbonplan-data
Version: 0.4.4
Summary: Preprocessing utilities for CarbonPlan's data catalog
Author-email: CarbonPlan <tech@carbonplan.org>
License: MIT
Project-URL: repository, https://github.com/carbonplan/data
Classifier: Development Status :: 3 - Alpha
Classifier: License :: OSI Approved :: MIT License
Classifier: Operating System :: OS Independent
Classifier: Intended Audience :: Science/Research
Classifier: Programming Language :: Python
Classifier: Programming Language :: Python :: 3
Classifier: Programming Language :: Python :: 3.9
Classifier: Programming Language :: Python :: 3.10
Classifier: Programming Language :: Python :: 3.11
Classifier: Programming Language :: Python :: 3.12
Classifier: Topic :: Scientific/Engineering
Requires-Python: >=3.9
License-File: LICENSE
Requires-Dist: intake <=0.7.0
Requires-Dist: validators
Requires-Dist: wget
Requires-Dist: numpy
Requires-Dist: xarray
